<?xml version="1.0" encoding="UTF-8"?>
<repomd xmlns="http://linux.duke.edu/metadata/repo" xmlns:rpm="http://linux.duke.edu/metadata/rpm">
  <revision>1285724102</revision>
  <data type="other">
    <checksum type="sha256">5520c585f2535fa25bedd19500aa12192a02e340aed3e9a62d285e2a29e402ff</checksum>
    <timestamp>1285724102</timestamp>
    <size>391</size>
    <open-size>484</open-size>
    <open-checksum type="sha256">be9811a9bdc13059c0c78848d84043324e9c1ba73d77d5c05abc110b8bb2d19e</open-checksum>
    <location href="repodata/other.xml.gz"/>
  </data>
  <data type="filelists">
    <checksum type="sha256">14a1c023cae2693285a89fedf4e50aba78f7d702d2616165f932c5df0663a8cc</checksum>
    <timestamp>1285724102</timestamp>
    <size>436</size>
    <open-size>630</open-size>
    <open-checksum type="sha256">1661a8f5b45fc24d88d2f7197c4dea546cc6e29a6f311aaf625630836ad3493d</open-checksum>
    <location href="repodata/filelists.xml.gz"/>
  </data>
  <data type="primary">
    <checksum type="sha256">8c4d8bebc2756dd66a1537ec5f67ab41fd7e378f75351c621d32b5f18caa3a07</checksum>
    <timestamp>1285724102</timestamp>
    <size>905</size>
    <open-size>2038</open-size>
    <open-checksum type="sha256">a14c95f4e34634c34108d98fbdc04ee5d3fb12fbb31fe20899a393954ef5e4d8</open-checksum>
    <location href="repodata/primary.xml.gz"/>
  </data>
</repomd>
